odoo/addons/procurement_mto_analytic/README.rst
odoo/addons/procurement_mto_analytic/__init__.py
odoo/addons/procurement_mto_analytic/__manifest__.py
odoo/addons/procurement_mto_analytic/i18n/procurement_mto_analytic.pot
odoo/addons/procurement_mto_analytic/i18n/purchase_procurement_analytic.pot
odoo/addons/procurement_mto_analytic/models/__init__.py
odoo/addons/procurement_mto_analytic/models/procurement.py
odoo/addons/procurement_mto_analytic/models/purchase_order_line.py
odoo/addons/procurement_mto_analytic/models/sale_order.py
odoo/addons/procurement_mto_analytic/models/stock.py
odoo/addons/procurement_mto_analytic/readme/CONFIGURE.rst
odoo/addons/procurement_mto_analytic/readme/DESCRIPTION.rst
odoo/addons/procurement_mto_analytic/readme/USAGE.rst
odoo/addons/procurement_mto_analytic/static/description/icon.png
odoo/addons/procurement_mto_analytic/static/description/index.html
odoo/addons/procurement_mto_analytic/tests/__init__.py
odoo/addons/procurement_mto_analytic/tests/test_purchase_procurement_analytic.py
odoo11_addon_procurement_mto_analytic-11.0.1.0.0.99.dev7.dist-info/METADATA
odoo11_addon_procurement_mto_analytic-11.0.1.0.0.99.dev7.dist-info/WHEEL
odoo11_addon_procurement_mto_analytic-11.0.1.0.0.99.dev7.dist-info/top_level.txt
odoo11_addon_procurement_mto_analytic-11.0.1.0.0.99.dev7.dist-info/RECORD
